pycatalicism/__init__.py
pycatalicism/activation_config.py
pycatalicism/config.py
pycatalicism/init_conc_config.py
pycatalicism/logging_decorator.py
pycatalicism/measurement_config.py
pycatalicism/pycat.py
pycatalicism/calc/__init__.py
pycatalicism/calc/activity.py
pycatalicism/calc/calc.py
pycatalicism/calc/calculator.py
pycatalicism/calc/calculator_factory.py
pycatalicism/calc/calculatorexception.py
pycatalicism/calc/chromatec_crystal_composition_copy_paste_parser.py
pycatalicism/calc/co2_hydrogenation_exporter.py
pycatalicism/calc/co2_hydrogenation_plotter.py
pycatalicism/calc/co2hydrogenationcalculator.py
pycatalicism/calc/co2hydrogenationproductsbasiscalculator.py
pycatalicism/calc/co_oxidation_exporter.py
pycatalicism/calc/co_oxidation_plotter.py
pycatalicism/calc/conversion.py
pycatalicism/calc/cooxidationcalculator.py
pycatalicism/calc/exporter.py
pycatalicism/calc/exporter_factory.py
pycatalicism/calc/exporterexception.py
pycatalicism/calc/parser.py
pycatalicism/calc/parser_factory.py
pycatalicism/calc/parserexception.py
pycatalicism/calc/plotter.py
pycatalicism/calc/plotter_factory.py
pycatalicism/calc/plotterexception.py
pycatalicism/calc/rawdata.py
pycatalicism/calc/selectivity.py
pycatalicism/chromatograph/__init__.py
pycatalicism/chromatograph/chromatec_analytic_modbus.py
pycatalicism/chromatograph/chromatec_control_panel_modbus.py
pycatalicism/chromatograph/chromatec_crystal_5000.py
pycatalicism/chromatograph/chromatograph_exceptions.py
pycatalicism/chromatograph/chromatograph_logging.py
pycatalicism/chromatograph/logging_config.py
pycatalicism/chromatograph/modbus_converter.py
pycatalicism/furnace/__init__.py
pycatalicism/furnace/furnace_exceptions.py
pycatalicism/furnace/furnace_logging.py
pycatalicism/furnace/logging_config.py
pycatalicism/furnace/owen_protocol.py
pycatalicism/furnace/owen_tmp101.py
pycatalicism/mass_flow_controller/__init__.py
pycatalicism/mass_flow_controller/bronkhorst_f201cv.py
pycatalicism-2.0.2.dist-info/METADATA
pycatalicism-2.0.2.dist-info/WHEEL
pycatalicism-2.0.2.dist-info/entry_points.txt
pycatalicism-2.0.2.dist-info/top_level.txt
pycatalicism-2.0.2.dist-info/RECORD
