Metadata-Version: 2.1
Name: pycatalicism
Version: 2.0.2
Summary: Program controls catalytic activity of materials measurement equipment as well as calculations
Home-page: https://github.com/leybodv/pycatalicism
Author: Denis Leybo
Author-email: denis@leybo.xyz
Classifier: Programming Language :: Python :: 3
Classifier: License :: OSI Approved :: MIT License
Classifier: Operating System :: OS Independent
Requires-Python: >3.10.0
Requires-Dist: numpy (>=1.23.2)
Requires-Dist: matplotlib (>=3.5.3)
Requires-Dist: pyserial (>=3.5)
Requires-Dist: pymodbus (<2.6,>=2.5.3)
Requires-Dist: bronkhorst-propar (>=1.0)
